emrvalidator/__init__.py
emrvalidator/profiler.py
emrvalidator/py.typed
emrvalidator/reporters.py
emrvalidator/rules.py
emrvalidator/validator.py
tests/__init__.py
tests/test_profiler.py
tests/test_validator.py
emrvalidator-1.0.2.dist-info/METADATA
emrvalidator-1.0.2.dist-info/WHEEL
emrvalidator-1.0.2.dist-info/top_level.txt
emrvalidator-1.0.2.dist-info/RECORD
