Metadata-Version: 2.4
Name: emrvalidator
Version: 1.0.2
Summary: A Data Validation Tool for Healthcare Data
Author: Rohan Desai
Author-email: rohan.acme@gmail.com
License: MIT
Requires-Dist: pandas
